nextPermutation/__init__.py
nextPermutation/main.py
nextPermutation-0.0.1.dist-info/METADATA
nextPermutation-0.0.1.dist-info/WHEEL
nextPermutation-0.0.1.dist-info/top_level.txt
nextPermutation-0.0.1.dist-info/RECORD
