Metadata-Version: 2.1
Name: nextPermutation
Version: 0.0.1
Summary: A Python library to generate the next permutation for an array.
Author: Ishita Shokeen
Author-email: ishitashokeen9@gmail.com
Keywords: python,dsa,problem-solving
Classifier: Development Status :: 1 - Planning
Classifier: Intended Audience :: Developers
Classifier: Programming Language :: Python :: 3
Classifier: Operating System :: Unix
Classifier: Operating System :: MacOS :: MacOS X
Classifier: Operating System :: Microsoft :: Windows
